{
  "0": {
    "lastChecked": "2019-03-28 10:06:28.205684",
    "last_releases": {
      "latest_release": {
        "version": "23.0.0",
        "sha": "3e7acb70098ce2dabe2f71914568550f037210cd",
        "date": "2019-03-27 22:59:58",
        "author": "escapewindow"
      }
    }
  },
  "1": {
    "sha": "3e7acb70098ce2dabe2f71914568550f037210cd",
    "url": "https://github.com/mozilla-releng/scriptworker/commit/3e7acb70098ce2dabe2f71914568550f037210cd",
    "commiter_name": "escapewindow",
    "commiter_email": null,
    "commit_message": "23.0.0",
    "commit_date": "2019-03-27 22:59:58",
    "files_changed": [
      "CHANGELOG.md",
      "requirements/base.txt",
      "requirements/test.txt",
      "scriptworker/version.py",
      "setup.py",
      "version.json"
    ]
  },
  "2": {
    "sha": "3e7acb70098ce2dabe2f71914568550f037210cd",
    "url": "https://github.com/mozilla-releng/scriptworker/commit/3e7acb70098ce2dabe2f71914568550f037210cd",
    "commiter_name": "escapewindow",
    "commiter_email": null,
    "commit_message": "23.0.0",
    "commit_date": "2019-03-27 22:59:58",
    "files_changed": [
      "CHANGELOG.md",
      "requirements/base.txt",
      "requirements/test.txt",
      "scriptworker/version.py",
      "setup.py",
      "version.json"
    ]
  },
  "3": {
    "sha": "6c3698449ec5ae8ca363862d41c4a370cd101912",
    "url": "https://github.com/mozilla-releng/scriptworker/commit/6c3698449ec5ae8ca363862d41c4a370cd101912",
    "commiter_name": "JohanLorenzo",
    "commiter_email": null,
    "commit_message": "22.1.0",
    "commit_date": "2019-03-19 10:43:07",
    "files_changed": [
      "CHANGELOG.md",
      "version.json"
    ]
  },
  "4": {
    "sha": "30a54b0c8092698f23b570cf81560f8e1af3322c",
    "url": "https://github.com/mozilla-releng/scriptworker/commit/30a54b0c8092698f23b570cf81560f8e1af3322c",
    "commiter_name": "JohanLorenzo",
    "commiter_email": null,
    "commit_message": "Bug 1533791 - Support \"assume\" scopes",
    "commit_date": "2019-03-18 17:55:11",
    "files_changed": [
      "scriptworker/cot/verify.py",
      "scriptworker/github.py",
      "scriptworker/test/test_cot_verify.py",
      "scriptworker/test/test_github.py"
    ]
  },
  "5": {
    "sha": "4e9b5817085acbd7c2d75292d9b6f84ef90f6561",
    "url": "https://github.com/mozilla-releng/scriptworker/commit/4e9b5817085acbd7c2d75292d9b6f84ef90f6561",
    "commiter_name": "JohanLorenzo",
    "commiter_email": null,
    "commit_message": "22.0.1",
    "commit_date": "2019-03-13 12:57:58",
    "files_changed": [
      "CHANGELOG.md",
      "version.json"
    ]
  },
  "6": {
    "sha": "f01e70d2649055f2fda310e68bf8a06f8410b4b5",
    "url": "https://github.com/mozilla-releng/scriptworker/commit/f01e70d2649055f2fda310e68bf8a06f8410b4b5",
    "commiter_name": "JohanLorenzo",
    "commiter_email": null,
    "commit_message": "Bug 1534694 - Allow snapcraft beta scope on mozilla-release",
    "commit_date": "2019-03-13 09:57:44",
    "files_changed": [
      "scriptworker/constants.py"
    ]
  },
  "7": {
    "sha": "4e9b5817085acbd7c2d75292d9b6f84ef90f6561",
    "url": "https://github.com/mozilla-releng/scriptworker/commit/4e9b5817085acbd7c2d75292d9b6f84ef90f6561",
    "commiter_name": "JohanLorenzo",
    "commiter_email": null,
    "commit_message": "22.0.1",
    "commit_date": "2019-03-13 12:57:58",
    "files_changed": [
      "CHANGELOG.md",
      "version.json"
    ]
  },
  "8": {
    "sha": "f01e70d2649055f2fda310e68bf8a06f8410b4b5",
    "url": "https://github.com/mozilla-releng/scriptworker/commit/f01e70d2649055f2fda310e68bf8a06f8410b4b5",
    "commiter_name": "JohanLorenzo",
    "commiter_email": null,
    "commit_message": "Bug 1534694 - Allow snapcraft beta scope on mozilla-release",
    "commit_date": "2019-03-13 09:57:44",
    "files_changed": [
      "scriptworker/constants.py"
    ]
  },
  "9": {
    "sha": "83840ad6360d82346a9cca531c8c2e2b939d63c3",
    "url": "https://github.com/mozilla-releng/scriptworker/commit/83840ad6360d82346a9cca531c8c2e2b939d63c3",
    "commiter_name": "escapewindow",
    "commiter_email": null,
    "commit_message": "Merge pull request #314 from escapewindow/slugid-ascii  fix integration tests for taskcluster-client.py>=7.0.0 and slugid>=2.0.0",
    "commit_date": "2019-03-08 22:28:55",
    "files_changed": [
      "requirements/base.in",
      "scriptworker/test/test_integration.py"
    ]
  },
  "10": {
    "sha": "213d98bc222ba50c557eb16b2d3a49e17bddd17a",
    "url": "https://github.com/mozilla-releng/scriptworker/commit/213d98bc222ba50c557eb16b2d3a49e17bddd17a",
    "commiter_name": "escapewindow",
    "commiter_email": null,
    "commit_message": "fix integration tests for taskcluster-client.py>=7.0.0 and slugid>=2.0.0",
    "commit_date": "2019-03-08 20:07:25",
    "files_changed": [
      "requirements/base.in",
      "scriptworker/test/test_integration.py"
    ]
  },
  "11": {
    "sha": "d216c9d074385a457fe645dce996c369b25a1ef9",
    "url": "https://github.com/mozilla-releng/scriptworker/commit/d216c9d074385a457fe645dce996c369b25a1ef9",
    "commiter_name": "escapewindow",
    "commiter_email": null,
    "commit_message": "Merge pull request #294 from escapewindow/ed25519  bug 1492617 - Add ed25519 signature support to cot",
    "commit_date": "2019-03-07 20:14:48",
    "files_changed": [
      "CHANGELOG.md",
      "docs/cot_overview.rst",
      "requirements/base.in",
      "requirements/base.txt",
      "requirements/test.txt",
      "scripts/gen_ed25519_key.py",
      "scriptworker.yaml.tmpl",
      "scriptworker/constants.py",
      "scriptworker/cot/generate.py",
      "scriptworker/cot/verify.py",
      "scriptworker/ed25519.py",
      "scriptworker/exceptions.py",
      "scriptworker/test/data/binary.zip",
      "scriptworker/test/data/ed25519/docker-worker_private_key",
      "scriptworker/test/data/ed25519/docker-worker_public_key",
      "scriptworker/test/data/ed25519/foo.json",
      "scriptworker/test/data/ed25519/foo.json.scriptworker.sig",
      "scriptworker/test/data/ed25519/generic-worker_private_key",
      "scriptworker/test/data/ed25519/generic-worker_public_key",
      "scriptworker/test/data/ed25519/scriptworker_private_key",
      "scriptworker/test/data/ed25519/scriptworker_public_key",
      "scriptworker/test/data/good.json",
      "scriptworker/test/data/no_creds.json",
      "scriptworker/test/test_cot_generate.py",
      "scriptworker/test/test_cot_verify.py",
      "scriptworker/test/test_ed25519.py",
      "scriptworker/test/test_integration.py",
      "scriptworker/test/test_utils.py",
      "scriptworker/test/test_worker.py",
      "scriptworker/utils.py",
      "scriptworker/version.py",
      "setup.py",
      "version.json"
    ]
  },
  "12": {
    "sha": "4a8f0b2c415117e59bf5e98debedd39fccb53b15",
    "url": "https://github.com/mozilla-releng/scriptworker/commit/4a8f0b2c415117e59bf5e98debedd39fccb53b15",
    "commiter_name": "escapewindow",
    "commiter_email": null,
    "commit_message": "22.0.0",
    "commit_date": "2019-03-07 19:29:46",
    "files_changed": [
      "CHANGELOG.md",
      "requirements/base.in",
      "requirements/base.txt",
      "requirements/test.txt",
      "scriptworker/version.py",
      "setup.py",
      "version.json"
    ]
  },
  "13": {
    "sha": "58768476d7b5eeef969e67eb42cb01ac0d9ee117",
    "url": "https://github.com/mozilla-releng/scriptworker/commit/58768476d7b5eeef969e67eb42cb01ac0d9ee117",
    "commiter_name": "JohanLorenzo",
    "commiter_email": null,
    "commit_message": "21.0.0",
    "commit_date": "2019-03-05 14:17:09",
    "files_changed": [
      "CHANGELOG.md",
      "version.json"
    ]
  },
  "14": {
    "sha": "c27296959436eaa43b2fe11dfffb07eac3ee1273",
    "url": "https://github.com/mozilla-releng/scriptworker/commit/c27296959436eaa43b2fe11dfffb07eac3ee1273",
    "commiter_name": "JohanLorenzo",
    "commiter_email": null,
    "commit_message": "Bug 1529990 - Fix Mobile bustage",
    "commit_date": "2019-02-22 18:49:14",
    "files_changed": [
      "scriptworker/constants.py",
      "scriptworker/cot/verify.py",
      "scriptworker/github.py",
      "scriptworker/task.py",
      "scriptworker/test/test_cot_verify.py",
      "scriptworker/test/test_github.py",
      "scriptworker/test/test_task.py",
      "scriptworker/test/test_utils.py",
      "scriptworker/utils.py"
    ]
  },
  "15": {
    "sha": "58768476d7b5eeef969e67eb42cb01ac0d9ee117",
    "url": "https://github.com/mozilla-releng/scriptworker/commit/58768476d7b5eeef969e67eb42cb01ac0d9ee117",
    "commiter_name": "JohanLorenzo",
    "commiter_email": null,
    "commit_message": "21.0.0",
    "commit_date": "2019-03-05 14:17:09",
    "files_changed": [
      "CHANGELOG.md",
      "version.json"
    ]
  },
  "16": {
    "sha": "c27296959436eaa43b2fe11dfffb07eac3ee1273",
    "url": "https://github.com/mozilla-releng/scriptworker/commit/c27296959436eaa43b2fe11dfffb07eac3ee1273",
    "commiter_name": "JohanLorenzo",
    "commiter_email": null,
    "commit_message": "Bug 1529990 - Fix Mobile bustage",
    "commit_date": "2019-02-22 18:49:14",
    "files_changed": [
      "scriptworker/constants.py",
      "scriptworker/cot/verify.py",
      "scriptworker/github.py",
      "scriptworker/task.py",
      "scriptworker/test/test_cot_verify.py",
      "scriptworker/test/test_github.py",
      "scriptworker/test/test_task.py",
      "scriptworker/test/test_utils.py",
      "scriptworker/utils.py"
    ]
  },
  "17": {
    "sha": "58768476d7b5eeef969e67eb42cb01ac0d9ee117",
    "url": "https://github.com/mozilla-releng/scriptworker/commit/58768476d7b5eeef969e67eb42cb01ac0d9ee117",
    "commiter_name": "JohanLorenzo",
    "commiter_email": null,
    "commit_message": "21.0.0",
    "commit_date": "2019-03-05 14:17:09",
    "files_changed": [
      "CHANGELOG.md",
      "version.json"
    ]
  },
  "18": {
    "sha": "c27296959436eaa43b2fe11dfffb07eac3ee1273",
    "url": "https://github.com/mozilla-releng/scriptworker/commit/c27296959436eaa43b2fe11dfffb07eac3ee1273",
    "commiter_name": "JohanLorenzo",
    "commiter_email": null,
    "commit_message": "Bug 1529990 - Fix Mobile bustage",
    "commit_date": "2019-02-22 18:49:14",
    "files_changed": [
      "scriptworker/constants.py",
      "scriptworker/cot/verify.py",
      "scriptworker/github.py",
      "scriptworker/task.py",
      "scriptworker/test/test_cot_verify.py",
      "scriptworker/test/test_github.py",
      "scriptworker/test/test_task.py",
      "scriptworker/test/test_utils.py",
      "scriptworker/utils.py"
    ]
  },
  "19": {
    "sha": "58768476d7b5eeef969e67eb42cb01ac0d9ee117",
    "url": "https://github.com/mozilla-releng/scriptworker/commit/58768476d7b5eeef969e67eb42cb01ac0d9ee117",
    "commiter_name": "JohanLorenzo",
    "commiter_email": null,
    "commit_message": "21.0.0",
    "commit_date": "2019-03-05 14:17:09",
    "files_changed": [
      "CHANGELOG.md",
      "version.json"
    ]
  },
  "20": {
    "sha": "c27296959436eaa43b2fe11dfffb07eac3ee1273",
    "url": "https://github.com/mozilla-releng/scriptworker/commit/c27296959436eaa43b2fe11dfffb07eac3ee1273",
    "commiter_name": "JohanLorenzo",
    "commiter_email": null,
    "commit_message": "Bug 1529990 - Fix Mobile bustage",
    "commit_date": "2019-02-22 18:49:14",
    "files_changed": [
      "scriptworker/constants.py",
      "scriptworker/cot/verify.py",
      "scriptworker/github.py",
      "scriptworker/task.py",
      "scriptworker/test/test_cot_verify.py",
      "scriptworker/test/test_github.py",
      "scriptworker/test/test_task.py",
      "scriptworker/test/test_utils.py",
      "scriptworker/utils.py"
    ]
  },
  "21": {
    "sha": "58768476d7b5eeef969e67eb42cb01ac0d9ee117",
    "url": "https://github.com/mozilla-releng/scriptworker/commit/58768476d7b5eeef969e67eb42cb01ac0d9ee117",
    "commiter_name": "JohanLorenzo",
    "commiter_email": null,
    "commit_message": "21.0.0",
    "commit_date": "2019-03-05 14:17:09",
    "files_changed": [
      "CHANGELOG.md",
      "version.json"
    ]
  },
  "22": {
    "sha": "c27296959436eaa43b2fe11dfffb07eac3ee1273",
    "url": "https://github.com/mozilla-releng/scriptworker/commit/c27296959436eaa43b2fe11dfffb07eac3ee1273",
    "commiter_name": "JohanLorenzo",
    "commiter_email": null,
    "commit_message": "Bug 1529990 - Fix Mobile bustage",
    "commit_date": "2019-02-22 18:49:14",
    "files_changed": [
      "scriptworker/constants.py",
      "scriptworker/cot/verify.py",
      "scriptworker/github.py",
      "scriptworker/task.py",
      "scriptworker/test/test_cot_verify.py",
      "scriptworker/test/test_github.py",
      "scriptworker/test/test_task.py",
      "scriptworker/test/test_utils.py",
      "scriptworker/utils.py"
    ]
  },
  "23": {
    "sha": "58768476d7b5eeef969e67eb42cb01ac0d9ee117",
    "url": "https://github.com/mozilla-releng/scriptworker/commit/58768476d7b5eeef969e67eb42cb01ac0d9ee117",
    "commiter_name": "JohanLorenzo",
    "commiter_email": null,
    "commit_message": "21.0.0",
    "commit_date": "2019-03-05 14:17:09",
    "files_changed": [
      "CHANGELOG.md",
      "version.json"
    ]
  },
  "24": {
    "sha": "c27296959436eaa43b2fe11dfffb07eac3ee1273",
    "url": "https://github.com/mozilla-releng/scriptworker/commit/c27296959436eaa43b2fe11dfffb07eac3ee1273",
    "commiter_name": "JohanLorenzo",
    "commiter_email": null,
    "commit_message": "Bug 1529990 - Fix Mobile bustage",
    "commit_date": "2019-02-22 18:49:14",
    "files_changed": [
      "scriptworker/constants.py",
      "scriptworker/cot/verify.py",
      "scriptworker/github.py",
      "scriptworker/task.py",
      "scriptworker/test/test_cot_verify.py",
      "scriptworker/test/test_github.py",
      "scriptworker/test/test_task.py",
      "scriptworker/test/test_utils.py",
      "scriptworker/utils.py"
    ]
  },
  "25": {
    "sha": "58768476d7b5eeef969e67eb42cb01ac0d9ee117",
    "url": "https://github.com/mozilla-releng/scriptworker/commit/58768476d7b5eeef969e67eb42cb01ac0d9ee117",
    "commiter_name": "JohanLorenzo",
    "commiter_email": null,
    "commit_message": "21.0.0",
    "commit_date": "2019-03-05 14:17:09",
    "files_changed": [
      "CHANGELOG.md",
      "version.json"
    ]
  },
  "26": {
    "sha": "c27296959436eaa43b2fe11dfffb07eac3ee1273",
    "url": "https://github.com/mozilla-releng/scriptworker/commit/c27296959436eaa43b2fe11dfffb07eac3ee1273",
    "commiter_name": "JohanLorenzo",
    "commiter_email": null,
    "commit_message": "Bug 1529990 - Fix Mobile bustage",
    "commit_date": "2019-02-22 18:49:14",
    "files_changed": [
      "scriptworker/constants.py",
      "scriptworker/cot/verify.py",
      "scriptworker/github.py",
      "scriptworker/task.py",
      "scriptworker/test/test_cot_verify.py",
      "scriptworker/test/test_github.py",
      "scriptworker/test/test_task.py",
      "scriptworker/test/test_utils.py",
      "scriptworker/utils.py"
    ]
  },
  "27": {
    "sha": "58768476d7b5eeef969e67eb42cb01ac0d9ee117",
    "url": "https://github.com/mozilla-releng/scriptworker/commit/58768476d7b5eeef969e67eb42cb01ac0d9ee117",
    "commiter_name": "JohanLorenzo",
    "commiter_email": null,
    "commit_message": "21.0.0",
    "commit_date": "2019-03-05 14:17:09",
    "files_changed": [
      "CHANGELOG.md",
      "version.json"
    ]
  },
  "28": {
    "sha": "c27296959436eaa43b2fe11dfffb07eac3ee1273",
    "url": "https://github.com/mozilla-releng/scriptworker/commit/c27296959436eaa43b2fe11dfffb07eac3ee1273",
    "commiter_name": "JohanLorenzo",
    "commiter_email": null,
    "commit_message": "Bug 1529990 - Fix Mobile bustage",
    "commit_date": "2019-02-22 18:49:14",
    "files_changed": [
      "scriptworker/constants.py",
      "scriptworker/cot/verify.py",
      "scriptworker/github.py",
      "scriptworker/task.py",
      "scriptworker/test/test_cot_verify.py",
      "scriptworker/test/test_github.py",
      "scriptworker/test/test_task.py",
      "scriptworker/test/test_utils.py",
      "scriptworker/utils.py"
    ]
  },
  "29": {
    "sha": "58768476d7b5eeef969e67eb42cb01ac0d9ee117",
    "url": "https://github.com/mozilla-releng/scriptworker/commit/58768476d7b5eeef969e67eb42cb01ac0d9ee117",
    "commiter_name": "JohanLorenzo",
    "commiter_email": null,
    "commit_message": "21.0.0",
    "commit_date": "2019-03-05 14:17:09",
    "files_changed": [
      "CHANGELOG.md",
      "version.json"
    ]
  },
  "30": {
    "sha": "c27296959436eaa43b2fe11dfffb07eac3ee1273",
    "url": "https://github.com/mozilla-releng/scriptworker/commit/c27296959436eaa43b2fe11dfffb07eac3ee1273",
    "commiter_name": "JohanLorenzo",
    "commiter_email": null,
    "commit_message": "Bug 1529990 - Fix Mobile bustage",
    "commit_date": "2019-02-22 18:49:14",
    "files_changed": [
      "scriptworker/constants.py",
      "scriptworker/cot/verify.py",
      "scriptworker/github.py",
      "scriptworker/task.py",
      "scriptworker/test/test_cot_verify.py",
      "scriptworker/test/test_github.py",
      "scriptworker/test/test_task.py",
      "scriptworker/test/test_utils.py",
      "scriptworker/utils.py"
    ]
  },
  "31": {
    "sha": "58768476d7b5eeef969e67eb42cb01ac0d9ee117",
    "url": "https://github.com/mozilla-releng/scriptworker/commit/58768476d7b5eeef969e67eb42cb01ac0d9ee117",
    "commiter_name": "JohanLorenzo",
    "commiter_email": null,
    "commit_message": "21.0.0",
    "commit_date": "2019-03-05 14:17:09",
    "files_changed": [
      "CHANGELOG.md",
      "version.json"
    ]
  },
  "32": {
    "sha": "c27296959436eaa43b2fe11dfffb07eac3ee1273",
    "url": "https://github.com/mozilla-releng/scriptworker/commit/c27296959436eaa43b2fe11dfffb07eac3ee1273",
    "commiter_name": "JohanLorenzo",
    "commiter_email": null,
    "commit_message": "Bug 1529990 - Fix Mobile bustage",
    "commit_date": "2019-02-22 18:49:14",
    "files_changed": [
      "scriptworker/constants.py",
      "scriptworker/cot/verify.py",
      "scriptworker/github.py",
      "scriptworker/task.py",
      "scriptworker/test/test_cot_verify.py",
      "scriptworker/test/test_github.py",
      "scriptworker/test/test_task.py",
      "scriptworker/test/test_utils.py",
      "scriptworker/utils.py"
    ]
  },
  "33": {
    "sha": "58768476d7b5eeef969e67eb42cb01ac0d9ee117",
    "url": "https://github.com/mozilla-releng/scriptworker/commit/58768476d7b5eeef969e67eb42cb01ac0d9ee117",
    "commiter_name": "JohanLorenzo",
    "commiter_email": null,
    "commit_message": "21.0.0",
    "commit_date": "2019-03-05 14:17:09",
    "files_changed": [
      "CHANGELOG.md",
      "version.json"
    ]
  },
  "34": {
    "sha": "c27296959436eaa43b2fe11dfffb07eac3ee1273",
    "url": "https://github.com/mozilla-releng/scriptworker/commit/c27296959436eaa43b2fe11dfffb07eac3ee1273",
    "commiter_name": "JohanLorenzo",
    "commiter_email": null,
    "commit_message": "Bug 1529990 - Fix Mobile bustage",
    "commit_date": "2019-02-22 18:49:14",
    "files_changed": [
      "scriptworker/constants.py",
      "scriptworker/cot/verify.py",
      "scriptworker/github.py",
      "scriptworker/task.py",
      "scriptworker/test/test_cot_verify.py",
      "scriptworker/test/test_github.py",
      "scriptworker/test/test_task.py",
      "scriptworker/test/test_utils.py",
      "scriptworker/utils.py"
    ]
  },
  "35": {
    "sha": "58768476d7b5eeef969e67eb42cb01ac0d9ee117",
    "url": "https://github.com/mozilla-releng/scriptworker/commit/58768476d7b5eeef969e67eb42cb01ac0d9ee117",
    "commiter_name": "JohanLorenzo",
    "commiter_email": null,
    "commit_message": "21.0.0",
    "commit_date": "2019-03-05 14:17:09",
    "files_changed": [
      "CHANGELOG.md",
      "version.json"
    ]
  },
  "36": {
    "sha": "c27296959436eaa43b2fe11dfffb07eac3ee1273",
    "url": "https://github.com/mozilla-releng/scriptworker/commit/c27296959436eaa43b2fe11dfffb07eac3ee1273",
    "commiter_name": "JohanLorenzo",
    "commiter_email": null,
    "commit_message": "Bug 1529990 - Fix Mobile bustage",
    "commit_date": "2019-02-22 18:49:14",
    "files_changed": [
      "scriptworker/constants.py",
      "scriptworker/cot/verify.py",
      "scriptworker/github.py",
      "scriptworker/task.py",
      "scriptworker/test/test_cot_verify.py",
      "scriptworker/test/test_github.py",
      "scriptworker/test/test_task.py",
      "scriptworker/test/test_utils.py",
      "scriptworker/utils.py"
    ]
  },
  "37": {
    "sha": "58768476d7b5eeef969e67eb42cb01ac0d9ee117",
    "url": "https://github.com/mozilla-releng/scriptworker/commit/58768476d7b5eeef969e67eb42cb01ac0d9ee117",
    "commiter_name": "JohanLorenzo",
    "commiter_email": null,
    "commit_message": "21.0.0",
    "commit_date": "2019-03-05 14:17:09",
    "files_changed": [
      "CHANGELOG.md",
      "version.json"
    ]
  },
  "38": {
    "sha": "c27296959436eaa43b2fe11dfffb07eac3ee1273",
    "url": "https://github.com/mozilla-releng/scriptworker/commit/c27296959436eaa43b2fe11dfffb07eac3ee1273",
    "commiter_name": "JohanLorenzo",
    "commiter_email": null,
    "commit_message": "Bug 1529990 - Fix Mobile bustage",
    "commit_date": "2019-02-22 18:49:14",
    "files_changed": [
      "scriptworker/constants.py",
      "scriptworker/cot/verify.py",
      "scriptworker/github.py",
      "scriptworker/task.py",
      "scriptworker/test/test_cot_verify.py",
      "scriptworker/test/test_github.py",
      "scriptworker/test/test_task.py",
      "scriptworker/test/test_utils.py",
      "scriptworker/utils.py"
    ]
  },
  "39": {
    "sha": "dc088bae7a6ec942969b1e4a7f1180698a399153",
    "url": "https://github.com/mozilla-releng/scriptworker/commit/dc088bae7a6ec942969b1e4a7f1180698a399153",
    "commiter_name": "escapewindow",
    "commiter_email": null,
    "commit_message": "Merge pull request #312 from MihaiTabara/ciswitch  Fix ci-{admin,configuration} new home in scriptworker.",
    "commit_date": "2019-02-21 18:18:09",
    "files_changed": [
      "CHANGELOG.md",
      "scriptworker/constants.py",
      "scriptworker/cot/verify.py",
      "scriptworker/test/data/cotv4/projects.yml",
      "version.json"
    ]
  },
  "40": {
    "sha": "ef10d250243e4879ed481c12a97f8ffaa6ec301d",
    "url": "https://github.com/mozilla-releng/scriptworker/commit/ef10d250243e4879ed481c12a97f8ffaa6ec301d",
    "commiter_name": "MihaiTabara",
    "commiter_email": "tabara.mihai@gmail.com",
    "commit_message": "20.0.1",
    "commit_date": "2019-02-21 17:53:32",
    "files_changed": [
      "CHANGELOG.md",
      "version.json"
    ]
  },
  "41": {
    "sha": "b6c1f101819d6f73059b935d4e2b46403bf07efa",
    "url": "https://github.com/mozilla-releng/scriptworker/commit/b6c1f101819d6f73059b935d4e2b46403bf07efa",
    "commiter_name": "JohanLorenzo",
    "commiter_email": null,
    "commit_message": "Enable mozilla-mobile staging release from Github forks",
    "commit_date": "2018-11-09 14:59:11",
    "files_changed": [
      "scriptworker/constants.py",
      "scriptworker/cot/verify.py",
      "scriptworker/test/test_cot_verify.py",
      "scriptworker/test/test_task.py"
    ]
  },
  "42": {
    "sha": "1492109d31f3075d27b44cd321b9cd267e1f8709",
    "url": "https://github.com/mozilla-releng/scriptworker/commit/1492109d31f3075d27b44cd321b9cd267e1f8709",
    "commiter_name": "escapewindow",
    "commiter_email": null,
    "commit_message": "17.1.1",
    "commit_date": "2019-01-03 00:21:43",
    "files_changed": [
      "CHANGELOG.md",
      "scriptworker/version.py",
      "version.json"
    ]
  },
  "43": {
    "sha": "b6c1f101819d6f73059b935d4e2b46403bf07efa",
    "url": "https://github.com/mozilla-releng/scriptworker/commit/b6c1f101819d6f73059b935d4e2b46403bf07efa",
    "commiter_name": "JohanLorenzo",
    "commiter_email": null,
    "commit_message": "Enable mozilla-mobile staging release from Github forks",
    "commit_date": "2018-11-09 14:59:11",
    "files_changed": [
      "scriptworker/constants.py",
      "scriptworker/cot/verify.py",
      "scriptworker/test/test_cot_verify.py",
      "scriptworker/test/test_task.py"
    ]
  },
  "44": {
    "sha": "1492109d31f3075d27b44cd321b9cd267e1f8709",
    "url": "https://github.com/mozilla-releng/scriptworker/commit/1492109d31f3075d27b44cd321b9cd267e1f8709",
    "commiter_name": "escapewindow",
    "commiter_email": null,
    "commit_message": "17.1.1",
    "commit_date": "2019-01-03 00:21:43",
    "files_changed": [
      "CHANGELOG.md",
      "scriptworker/version.py",
      "version.json"
    ]
  },
  "45": {
    "sha": "453af4e8c6b243058cc29ef9e85b4c450715489e",
    "url": "https://github.com/mozilla-releng/scriptworker/commit/453af4e8c6b243058cc29ef9e85b4c450715489e",
    "commiter_name": "escapewindow",
    "commiter_email": null,
    "commit_message": "Merge pull request #291 from djmitche/bug1517201  Bug 1517201 - support reading action.extra.actionPerm",
    "commit_date": "2019-01-03 00:18:40",
    "files_changed": [
      "scriptworker/cot/verify.py"
    ]
  },
  "46": {
    "sha": "a5f8d14be2f56daa39d8d3518cf18e3d7ac95792",
    "url": "https://github.com/mozilla-releng/scriptworker/commit/a5f8d14be2f56daa39d8d3518cf18e3d7ac95792",
    "commiter_name": "djmitche",
    "commiter_email": "dustin@v.igoro.us",
    "commit_message": "Bug 1517201 - support reading action.extra.actionPerm",
    "commit_date": "2019-01-02 23:48:05",
    "files_changed": [
      "scriptworker/cot/verify.py"
    ]
  },
  "47": {
    "sha": "a86e056c8526238d690bd31a323d7adec6d13cb7",
    "url": "https://github.com/mozilla-releng/scriptworker/commit/a86e056c8526238d690bd31a323d7adec6d13cb7",
    "commiter_name": "escapewindow",
    "commiter_email": null,
    "commit_message": "Merge pull request #286 from escapewindow/action-hook4  bug 1485680 - convert release-promotion to an action hook",
    "commit_date": "2018-12-28 19:36:44",
    "files_changed": [
      "CHANGELOG.md",
      "requirements/base.txt",
      "requirements/test.txt",
      "scriptworker/cot/verify.py",
      "scriptworker/test/data/cotv2/actions.json",
      "scriptworker/test/data/cotv2/cotv4_relpro_context.json",
      "scriptworker/test/data/cotv2/cotv4_relpro_template.json",
      "scriptworker/test/data/cotv3/.taskcluster.yml",
      "scriptworker/test/data/cotv3/action_retrigger.json",
      "scriptworker/test/data/cotv3/actions.json",
      "scriptworker/test/data/cotv3/decision_try.json",
      "scriptworker/test/data/cotv3/parameters.yml",
      "scriptworker/test/data/cotv3/pushlog.json",
      "scriptworker/test/data/cotv4/.taskcluster.yml",
      "scriptworker/test/data/cotv4/action_relpro.json",
      "scriptworker/test/data/cotv4/action_retrigger.json",
      "scriptworker/test/data/cotv4/actions.json",
      "scriptworker/test/data/cotv4/decision_try.json",
      "scriptworker/test/data/cotv4/parameters.yml",
      "scriptworker/test/data/cotv4/projects.yml",
      "scriptworker/test/data/cotv4/pushlog.json",
      "scriptworker/test/data/cotv4/retrigger_context.json",
      "scriptworker/test/data/cotv4/retrigger_template.json",
      "scriptworker/test/test_cot_verify.py",
      "scriptworker/version.py",
      "version.json"
    ]
  },
  "48": {
    "sha": "c8c416e70e3e796449c639876a9dd12307829512",
    "url": "https://github.com/mozilla-releng/scriptworker/commit/c8c416e70e3e796449c639876a9dd12307829512",
    "commiter_name": "escapewindow",
    "commiter_email": null,
    "commit_message": "17.1.0",
    "commit_date": "2018-12-28 19:29:07",
    "files_changed": [
      "CHANGELOG.md",
      "requirements/base.txt",
      "requirements/test.txt",
      "scriptworker/version.py",
      "version.json"
    ]
  },
  "49": {
    "sha": "b71d1aafd9db05f3ee8e917af7faba5c92ae6881",
    "url": "https://github.com/mozilla-releng/scriptworker/commit/b71d1aafd9db05f3ee8e917af7faba5c92ae6881",
    "commiter_name": "escapewindow",
    "commiter_email": null,
    "commit_message": "address tomprince's review comments",
    "commit_date": "2018-12-28 18:54:11",
    "files_changed": [
      "scriptworker/cot/verify.py",
      "scriptworker/test/data/cotv4/broken_actions.json",
      "scriptworker/test/test_cot_verify.py"
    ]
  }
}