{
  "0": {
    "last_checked": "2019-06-27T18:40:47.559885"
  },
  "1": {
    "sha": "4059cbddade02ce143cb9b1e32ef383e378d7d14",
    "url": "https://api.github.com/repos/mozilla-releng/OpenCloudConfig/commits/4059cbddade02ce143cb9b1e32ef383e378d7d14",
    "author": "Pete Moore",
    "author_email": "pmoore@mozilla.com",
    "message": "Testing generic-worker 15.1.0 / taskcluster-proxy 5.1.0 on *STAGING*\n\nThis change does _not_ affect any production workers. Commit made with:\n\n    ./gecko-try.sh 15.1.0 5.1.0\n\nSee https://github.com/taskcluster/generic-worker/blob/7e84aea3e701b9cfa7f4dae2a382977fc771f9bf/mozilla-try-scripts/gecko-try.sh\n\ndeploy: gecko-1-b-win2012-beta gecko-t-win10-64-beta gecko-t-win10-64-cu gecko-t-win10-64-gpu-b gecko-t-win7-32-beta gecko-t-win7-32-cu gecko-t-win7-32-gpu-b",
    "date": "2019-06-27T08:44:16Z",
    "files": "This commit contains 7 files changed."
  },
  "2": {
    "sha": "b41bfcd83b34a9dddcb49a83e014eb9e917a8bcf",
    "url": "https://api.github.com/repos/mozilla-releng/OpenCloudConfig/commits/b41bfcd83b34a9dddcb49a83e014eb9e917a8bcf",
    "author": "Pete Moore",
    "author_email": "pmoore@mozilla.com",
    "message": "Trying another patched version of generic-worker on gecko-t-win7-32-cu and gecko-t-win10-64-cu\n\ndeploy: gecko-t-win7-32-cu gecko-t-win10-64-cu",
    "date": "2019-06-26T09:32:08Z",
    "files": "This commit contains 2 files changed."
  },
  "3": {
    "sha": "7b1c167d9a1029bf29018bf3a63a853c8ded3350",
    "url": "https://api.github.com/repos/mozilla-releng/OpenCloudConfig/commits/7b1c167d9a1029bf29018bf3a63a853c8ded3350",
    "author": "Pete Moore",
    "author_email": "pmoore@mozilla.com",
    "message": "Trying another patched version of generic-worker on gecko-t-win7-32-cu and gecko-t-win10-64-cu\n\ndeploy: gecko-t-win7-32-cu gecko-t-win10-64-cu",
    "date": "2019-06-26T08:06:22Z",
    "files": "This commit contains 2 files changed."
  },
  "4": {
    "sha": "337f14482cf019a58e0a1de97a51811969de2271",
    "url": "https://api.github.com/repos/mozilla-releng/OpenCloudConfig/commits/337f14482cf019a58e0a1de97a51811969de2271",
    "author": "Pete Moore",
    "author_email": "pmoore@mozilla.com",
    "message": "Trying another patched version of generic-worker on gecko-t-win7-32-cu and gecko-t-win10-64-cu\n\ndeploy: gecko-t-win7-32-cu gecko-t-win10-64-cu",
    "date": "2019-06-26T03:37:11Z",
    "files": "This commit contains 2 files changed."
  },
  "5": {
    "sha": "d98b8af7d1a2fcb015a73beb9229ea21e3ef8137",
    "url": "https://api.github.com/repos/mozilla-releng/OpenCloudConfig/commits/d98b8af7d1a2fcb015a73beb9229ea21e3ef8137",
    "author": "Pete Moore",
    "author_email": "pmoore@mozilla.com",
    "message": "Trying patched version of generic-worker on gecko-t-win7-32-cu and gecko-t-win10-64-cu\n\ndeploy: gecko-t-win7-32-cu gecko-t-win10-64-cu",
    "date": "2019-06-25T20:12:50Z",
    "files": "This commit contains 2 files changed."
  },
  "6": {
    "sha": "a6013b2cb4afda95b789d477f85f16ad0ec0179f",
    "url": "https://api.github.com/repos/mozilla-releng/OpenCloudConfig/commits/a6013b2cb4afda95b789d477f85f16ad0ec0179f",
    "author": "Pete Moore",
    "author_email": "pmoore@mozilla.com",
    "message": "Rolling back STAGING changes from today\n\ndeploy: gecko-1-b-win2012-beta gecko-t-win10-64-beta gecko-t-win10-64-cu gecko-t-win10-64-gpu-b gecko-t-win7-32-beta gecko-t-win7-32-cu gecko-t-win7-32-gpu-b",
    "date": "2019-06-25T19:43:53Z",
    "files": "This commit contains 7 files changed."
  },
  "7": {
    "sha": "0137c4adf1aa16c796c9f94c269d2951ef93462b",
    "url": "https://api.github.com/repos/mozilla-releng/OpenCloudConfig/commits/0137c4adf1aa16c796c9f94c269d2951ef93462b",
    "author": "Pete Moore",
    "author_email": "pmoore@mozilla.com",
    "message": "Fix to previous staging change\n\ndeploy: gecko-1-b-win2012-beta gecko-t-win10-64-beta gecko-t-win10-64-cu gecko-t-win10-64-gpu-b gecko-t-win7-32-beta gecko-t-win7-32-cu gecko-t-win7-32-gpu-b",
    "date": "2019-06-25T18:21:44Z",
    "files": "This commit contains 7 files changed."
  },
  "8": {
    "sha": "b39b5d158c705c10469c4a3fd1039b7b77a4a996",
    "url": "https://api.github.com/repos/mozilla-releng/OpenCloudConfig/commits/b39b5d158c705c10469c4a3fd1039b7b77a4a996",
    "author": "Pete Moore",
    "author_email": "pmoore@mozilla.com",
    "message": "Testing generic-worker 15.0.2 / taskcluster-proxy 5.1.0 on *STAGING*\n\nThis change does _not_ affect any production workers. Commit made with:\n\n    ./gecko-try.sh 15.0.2 5.1.0\n\nSee https://github.com/taskcluster/generic-worker/blob/c808fafd96da532bb84f1b9df6e963dc19fce172/mozilla-try-scripts/gecko-try.sh\n\ndeploy: gecko-1-b-win2012-beta gecko-t-win10-64-beta gecko-t-win10-64-cu gecko-t-win10-64-gpu-b gecko-t-win7-32-beta gecko-t-win7-32-cu gecko-t-win7-32-gpu-b",
    "date": "2019-06-25T18:16:14Z",
    "files": "This commit contains 7 files changed."
  }
}